CHANGELOG.md
LICENSE
MANIFEST.in
README.md
setup.cfg
setup.py
eic_aichat_users/__init__.py
eic_aichat_users.egg-info/PKG-INFO
eic_aichat_users.egg-info/SOURCES.txt
eic_aichat_users.egg-info/dependency_links.txt
eic_aichat_users.egg-info/requires.txt
eic_aichat_users.egg-info/top_level.txt
eic_aichat_users.egg-info/zip-safe
eic_aichat_users/accounts/__init__.py
eic_aichat_users/accounts/data/AccountActivityTypeV1.py
eic_aichat_users/accounts/data/AccountV1.py
eic_aichat_users/accounts/data/AccountV1Schema.py
eic_aichat_users/accounts/data/__init__.py
eic_aichat_users/accounts/logic/AccountsService.py
eic_aichat_users/accounts/logic/IAccountsService.py
eic_aichat_users/accounts/logic/__init__.py
eic_aichat_users/accounts/persistence/AccountsMemoryPersistence.py
eic_aichat_users/accounts/persistence/AccountsMongoDbPersistence.py
eic_aichat_users/accounts/persistence/IAccountsPersistence.py
eic_aichat_users/accounts/persistence/__init__.py
eic_aichat_users/activities/__init__.py
eic_aichat_users/activities/data/PartyActivityV1.py
eic_aichat_users/activities/data/PartyActivityV1Schema.py
eic_aichat_users/activities/data/ReferenceV1.py
eic_aichat_users/activities/data/ReferenceV1Schema.py
eic_aichat_users/activities/data/__init__.py
eic_aichat_users/activities/logic/ActivitiesCommandSet.py
eic_aichat_users/activities/logic/ActivitiesService.py
eic_aichat_users/activities/logic/IActivitiesService.py
eic_aichat_users/activities/logic/__init__.py
eic_aichat_users/activities/persistence/ActivitiesMemoryPersistence.py
eic_aichat_users/activities/persistence/ActivitiesMongoDbPersistence.py
eic_aichat_users/activities/persistence/IActivitiesPersistence.py
eic_aichat_users/activities/persistence/__init__.py
eic_aichat_users/build/AIChatUsersFactory.py
eic_aichat_users/build/__init__.py
eic_aichat_users/groupmemberships/__init__.py
eic_aichat_users/groupmemberships/data/GroupMembershipV1.py
eic_aichat_users/groupmemberships/data/GroupMembershipV1Schema.py
eic_aichat_users/groupmemberships/data/__init__.py
eic_aichat_users/groupmemberships/logic/GroupMembershipsService.py
eic_aichat_users/groupmemberships/logic/IGroupMembershipsService.py
eic_aichat_users/groupmemberships/logic/__init__.py
