Metadata-Version: 2.1
Name: eic-aichat-users
Version: 1.0.61
Summary: AI Chat Users in Python
Home-page: https://bitbucket.org/entinco/eic-ai-prototypes/src/master/lib-aichatusers-python
Author: Enterprise Innovation Consulting LLC
Author-email: seroukhov@entinco.com
License: Commercial
Platform: any
Classifier: Intended Audience :: Developers
Classifier: License :: Other/Proprietary License
Classifier: Operating System :: OS Independent
Classifier: Programming Language :: Python
Classifier: Programming Language :: Python :: 3.12
Classifier: Programming Language :: Python :: 3.12
Classifier: Programming Language :: Python :: 3.12
Classifier: Programming Language :: Python :: 3.12
Classifier: Topic :: Software Development :: Libraries :: Python Modules
License-File: LICENSE
